README.md
setup.py
Prix_Carburant_FR_Client_v2.egg-info/PKG-INFO
Prix_Carburant_FR_Client_v2.egg-info/SOURCES.txt
Prix_Carburant_FR_Client_v2.egg-info/dependency_links.txt
Prix_Carburant_FR_Client_v2.egg-info/entry_points.txt
Prix_Carburant_FR_Client_v2.egg-info/top_level.txt
prixCarburantClient/prixCarburantClient.py