Metadata-Version: 2.1
Name: Prix-Carburant-FR-Client-v2
Version: 1.0.3
Summary: StationEssence client
Home-page: https://github.com/Marc-06/essence
Author: Maxime Wantiez, Yann RITTER
Author-email:  
License: MIT
Platform: UNKNOWN
